{
  "character": "Link",
  "slug": "Link",
  "scrapedAt": "2026-07-16T23:32:37.723Z",
  "jumpSquat": 6,
  "weight": 104,
  "wavedashOOSFrames": 16,
  "wikiUrl": "https://www.ssbwiki.com/Link_(SSBM)",
  "moves": [
    {
      "move": "Edge attack",
      "type": 8,
      "isUpSpecial": false,
      "startup": null,
      "hitboxes": [
        {
          "hitbox": "Slow",
          "shieldSafety": null,
          "shieldRaw": null,
          "damage": 8,
          "knockbackGrowth": 100,
          "baseKnockback": 0,
          "setKnockback": 90,
          "angle": 361,
          "endlag": null
        },
        {
          "hitbox": "Slow",
          "shieldSafety": null,
          "shieldRaw": null,
          "damage": 8,
          "knockbackGrowth": 100,
          "baseKnockback": 0,
          "setKnockback": 90,
          "angle": 361,
          "endlag": null
        },
        {
          "hitbox": "Fast",
          "shieldSafety": null,
          "shieldRaw": null,
          "damage": 8,
          "knockbackGrowth": 100,
          "baseKnockback": 0,
          "setKnockback": 90,
          "angle": 361,
          "endlag": null
        },
        {
          "hitbox": "Fast",
          "shieldSafety": null,
          "shieldRaw": null,
          "damage": 8,
          "knockbackGrowth": 100,
          "baseKnockback": 0,
          "setKnockback": 90,
          "angle": 361,
          "endlag": null
        }
      ]
    },
    {
      "move": "Pummel",
      "type": 6,
      "isUpSpecial": false,
      "startup": null,
      "hitboxes": [
        {
          "hitbox": "Id0",
          "shieldSafety": null,
          "shieldRaw": null,
          "damage": 3,
          "knockbackGrowth": 100,
          "baseKnockback": 0,
          "setKnockback": 0,
          "angle": 361,
          "endlag": null
        }
      ]
    },
    {
      "move": "Forward throw",
      "type": 6,
      "isUpSpecial": false,
      "startup": 12,
      "hitboxes": [
        {
          "hitbox": "Id0",
          "shieldSafety": {
            "min": -24,
            "max": -24
          },
          "shieldRaw": "-24",
          "damage": 3,
          "knockbackGrowth": 0,
          "baseKnockback": 0,
          "setKnockback": 90,
          "angle": 361,
          "endlag": 24
        },
        {
          "hitbox": "Id1",
          "shieldSafety": {
            "min": -24,
            "max": -24
          },
          "shieldRaw": "-24",
          "damage": 3,
          "knockbackGrowth": 0,
          "baseKnockback": 0,
          "setKnockback": 90,
          "angle": 361,
          "endlag": 24
        }
      ]
    },
    {
      "move": "Back throw",
      "type": 6,
      "isUpSpecial": false,
      "startup": 11,
      "hitboxes": [
        {
          "hitbox": "Id0",
          "shieldSafety": {
            "min": -25,
            "max": -25
          },
          "shieldRaw": "-25",
          "damage": 3,
          "knockbackGrowth": 0,
          "baseKnockback": 0,
          "setKnockback": 90,
          "angle": 361,
          "endlag": 24
        },
        {
          "hitbox": "Id1",
          "shieldSafety": {
            "min": -25,
            "max": -25
          },
          "shieldRaw": "-25",
          "damage": 3,
          "knockbackGrowth": 0,
          "baseKnockback": 0,
          "setKnockback": 90,
          "angle": 361,
          "endlag": 24
        }
      ]
    },
    {
      "move": "Up throw",
      "type": 6,
      "isUpSpecial": false,
      "startup": 26,
      "hitboxes": [
        {
          "hitbox": "Id0",
          "shieldSafety": {
            "min": -20,
            "max": -20
          },
          "shieldRaw": "-20",
          "damage": 4,
          "knockbackGrowth": 100,
          "baseKnockback": 50,
          "setKnockback": 0,
          "angle": 20,
          "endlag": 23
        },
        {
          "hitbox": "Id1",
          "shieldSafety": {
            "min": -20,
            "max": -20
          },
          "shieldRaw": "-20",
          "damage": 4,
          "knockbackGrowth": 100,
          "baseKnockback": 50,
          "setKnockback": 0,
          "angle": 20,
          "endlag": 23
        }
      ]
    },
    {
      "move": "Down throw",
      "type": 6,
      "isUpSpecial": false,
      "startup": 22,
      "hitboxes": [
        {
          "hitbox": "Id0",
          "shieldSafety": {
            "min": -25,
            "max": -25
          },
          "shieldRaw": "-25",
          "damage": 2,
          "knockbackGrowth": 0,
          "baseKnockback": 0,
          "setKnockback": 90,
          "angle": 361,
          "endlag": 26
        }
      ]
    },
    {
      "move": "Down Air",
      "type": 3,
      "isUpSpecial": false,
      "startup": 13,
      "hitboxes": [
        {
          "hitbox": "Id0",
          "shieldSafety": {
            "min": -39,
            "max": -14
          },
          "shieldRaw": "-39/-14",
          "damage": 22,
          "knockbackGrowth": 80,
          "baseKnockback": 50,
          "setKnockback": 0,
          "angle": 65,
          "endlag": 25
        },
        {
          "hitbox": "Id1",
          "shieldSafety": {
            "min": -40,
            "max": -15
          },
          "shieldRaw": "-40/-15",
          "damage": 20,
          "knockbackGrowth": 80,
          "baseKnockback": 40,
          "setKnockback": 0,
          "angle": 65,
          "endlag": 25
        },
        {
          "hitbox": "Id2",
          "shieldSafety": {
            "min": -40,
            "max": -15
          },
          "shieldRaw": "-40/-15",
          "damage": 20,
          "knockbackGrowth": 80,
          "baseKnockback": 40,
          "setKnockback": 0,
          "angle": 65,
          "endlag": 25
        },
        {
          "hitbox": "Id0",
          "shieldSafety": {
            "min": -40,
            "max": -15
          },
          "shieldRaw": "-40/-15",
          "damage": 19,
          "knockbackGrowth": 80,
          "baseKnockback": 50,
          "setKnockback": 0,
          "angle": 65,
          "endlag": 25
        },
        {
          "hitbox": "Id1",
          "shieldSafety": {
            "min": -40,
            "max": -15
          },
          "shieldRaw": "-40/-15",
          "damage": 19,
          "knockbackGrowth": 80,
          "baseKnockback": 40,
          "setKnockback": 0,
          "angle": 65,
          "endlag": 25
        },
        {
          "hitbox": "Id2",
          "shieldSafety": {
            "min": -40,
            "max": -15
          },
          "shieldRaw": "-40/-15",
          "damage": 19,
          "knockbackGrowth": 80,
          "baseKnockback": 40,
          "setKnockback": 0,
          "angle": 65,
          "endlag": 25
        }
      ]
    },
    {
      "move": "Up Air",
      "type": 3,
      "isUpSpecial": false,
      "startup": 5,
      "hitboxes": [
        {
          "hitbox": "Id0",
          "shieldSafety": {
            "min": -21,
            "max": -6
          },
          "shieldRaw": "-21/-6",
          "damage": 16,
          "knockbackGrowth": 85,
          "baseKnockback": 25,
          "setKnockback": 0,
          "angle": 80,
          "endlag": 15
        },
        {
          "hitbox": "Id1",
          "shieldSafety": {
            "min": -21,
            "max": -6
          },
          "shieldRaw": "-21/-6",
          "damage": 16,
          "knockbackGrowth": 85,
          "baseKnockback": 25,
          "setKnockback": 0,
          "angle": 80,
          "endlag": 15
        },
        {
          "hitbox": "Id2",
          "shieldSafety": {
            "min": -21,
            "max": -6
          },
          "shieldRaw": "-21/-6",
          "damage": 16,
          "knockbackGrowth": 85,
          "baseKnockback": 25,
          "setKnockback": 0,
          "angle": 80,
          "endlag": 15
        },
        {
          "hitbox": "Id0",
          "shieldSafety": {
            "min": -23,
            "max": -8
          },
          "shieldRaw": "-23/-8",
          "damage": 12,
          "knockbackGrowth": 85,
          "baseKnockback": 25,
          "setKnockback": 0,
          "angle": 80,
          "endlag": 15
        },
        {
          "hitbox": "Id1",
          "shieldSafety": {
            "min": -23,
            "max": -8
          },
          "shieldRaw": "-23/-8",
          "damage": 12,
          "knockbackGrowth": 85,
          "baseKnockback": 25,
          "setKnockback": 0,
          "angle": 80,
          "endlag": 15
        },
        {
          "hitbox": "Id2",
          "shieldSafety": {
            "min": -23,
            "max": -8
          },
          "shieldRaw": "-23/-8",
          "damage": 12,
          "knockbackGrowth": 85,
          "baseKnockback": 25,
          "setKnockback": 0,
          "angle": 80,
          "endlag": 15
        }
      ]
    },
    {
      "move": "Forward Air",
      "type": 3,
      "isUpSpecial": false,
      "startup": 14,
      "hitboxes": [
        {
          "hitbox": "Id0",
          "shieldSafety": {
            "min": -8,
            "max": 0
          },
          "shieldRaw": "-8/0",
          "damage": 13,
          "knockbackGrowth": 100,
          "baseKnockback": 5,
          "setKnockback": 0,
          "angle": 361,
          "endlag": 7
        },
        {
          "hitbox": "Id1",
          "shieldSafety": {
            "min": -8,
            "max": 0
          },
          "shieldRaw": "-8/0",
          "damage": 13,
          "knockbackGrowth": 100,
          "baseKnockback": 5,
          "setKnockback": 0,
          "angle": 361,
          "endlag": 7
        },
        {
          "hitbox": "Id2",
          "shieldSafety": {
            "min": -8,
            "max": 0
          },
          "shieldRaw": "-8/0",
          "damage": 13,
          "knockbackGrowth": 100,
          "baseKnockback": 5,
          "setKnockback": 0,
          "angle": 361,
          "endlag": 7
        },
        {
          "hitbox": "Id3",
          "shieldSafety": {
            "min": -8,
            "max": 0
          },
          "shieldRaw": "-8/0",
          "damage": 13,
          "knockbackGrowth": 100,
          "baseKnockback": 5,
          "setKnockback": 0,
          "angle": 361,
          "endlag": 7
        },
        {
          "hitbox": "Id0",
          "shieldSafety": {
            "min": -10,
            "max": -2
          },
          "shieldRaw": "-10/-2",
          "damage": 8,
          "knockbackGrowth": 90,
          "baseKnockback": 0,
          "setKnockback": 0,
          "angle": 361,
          "endlag": 7
        },
        {
          "hitbox": "Id1",
          "shieldSafety": {
            "min": -10,
            "max": -2
          },
          "shieldRaw": "-10/-2",
          "damage": 8,
          "knockbackGrowth": 90,
          "baseKnockback": 0,
          "setKnockback": 0,
          "angle": 361,
          "endlag": 7
        },
        {
          "hitbox": "Id2",
          "shieldSafety": {
            "min": -10,
            "max": -2
          },
          "shieldRaw": "-10/-2",
          "damage": 8,
          "knockbackGrowth": 90,
          "baseKnockback": 0,
          "setKnockback": 0,
          "angle": 361,
          "endlag": 7
        },
        {
          "hitbox": "Id3",
          "shieldSafety": {
            "min": -10,
            "max": -2
          },
          "shieldRaw": "-10/-2",
          "damage": 8,
          "knockbackGrowth": 90,
          "baseKnockback": 0,
          "setKnockback": 0,
          "angle": 361,
          "endlag": 7
        }
      ]
    },
    {
      "move": "Up Special",
      "type": 4,
      "isUpSpecial": true,
      "startup": 8,
      "hitboxes": [
        {
          "hitbox": "Grounded Sweetspot",
          "shieldSafety": {
            "min": -71,
            "max": -71
          },
          "shieldRaw": "-71",
          "damage": 15,
          "knockbackGrowth": 95,
          "baseKnockback": 32,
          "setKnockback": 0,
          "angle": 361,
          "endlag": 79
        },
        {
          "hitbox": "Grounded Sweetspot",
          "shieldSafety": {
            "min": -71,
            "max": -71
          },
          "shieldRaw": "-71",
          "damage": 15,
          "knockbackGrowth": 95,
          "baseKnockback": 32,
          "setKnockback": 0,
          "angle": 361,
          "endlag": 79
        },
        {
          "hitbox": "Grounded Sweetspot",
          "shieldSafety": {
            "min": -71,
            "max": -71
          },
          "shieldRaw": "-71",
          "damage": 15,
          "knockbackGrowth": 95,
          "baseKnockback": 32,
          "setKnockback": 0,
          "angle": 361,
          "endlag": 79
        },
        {
          "hitbox": "Grounded Sweetspot",
          "shieldSafety": {
            "min": -71,
            "max": -71
          },
          "shieldRaw": "-71",
          "damage": 15,
          "knockbackGrowth": 95,
          "baseKnockback": 32,
          "setKnockback": 0,
          "angle": 361,
          "endlag": 79
        },
        {
          "hitbox": "Grounded Late",
          "shieldSafety": {
            "min": -75,
            "max": -75
          },
          "shieldRaw": "-75",
          "damage": 5,
          "knockbackGrowth": 100,
          "baseKnockback": 60,
          "setKnockback": 0,
          "angle": 0,
          "endlag": 79
        },
        {
          "hitbox": "Grounded Late",
          "shieldSafety": {
            "min": -75,
            "max": -75
          },
          "shieldRaw": "-75",
          "damage": 5,
          "knockbackGrowth": 100,
          "baseKnockback": 60,
          "setKnockback": 0,
          "angle": 0,
          "endlag": 79
        },
        {
          "hitbox": "Grounded Late",
          "shieldSafety": {
            "min": -75,
            "max": -75
          },
          "shieldRaw": "-75",
          "damage": 5,
          "knockbackGrowth": 100,
          "baseKnockback": 60,
          "setKnockback": 0,
          "angle": 0,
          "endlag": 79
        }
      ]
    },
    {
      "move": "Neutral Special",
      "type": 4,
      "isUpSpecial": false,
      "startup": 18,
      "hitboxes": [
        {
          "hitbox": "Pointblank",
          "shieldSafety": {
            "isProjectile": true,
            "isStun": true,
            "min": 2,
            "max": 2
          },
          "shieldRaw": "2",
          "damage": 1,
          "knockbackGrowth": 50,
          "baseKnockback": 8,
          "setKnockback": 0,
          "angle": 70,
          "endlag": null
        },
        {
          "hitbox": "No Charge",
          "shieldSafety": {
            "isProjectile": true,
            "isStun": true,
            "min": 4,
            "max": 4
          },
          "shieldRaw": "4",
          "damage": 5,
          "knockbackGrowth": 50,
          "baseKnockback": 8,
          "setKnockback": 0,
          "angle": 70,
          "endlag": null
        },
        {
          "hitbox": "Level 1 Charge",
          "shieldSafety": {
            "isProjectile": true,
            "isStun": true,
            "min": 4,
            "max": 4
          },
          "shieldRaw": "4",
          "damage": 6,
          "knockbackGrowth": 50,
          "baseKnockback": 8,
          "setKnockback": 0,
          "angle": 70,
          "endlag": null
        },
        {
          "hitbox": "Level 2 Charge",
          "shieldSafety": {
            "isProjectile": true,
            "isStun": true,
            "min": 5,
            "max": 5
          },
          "shieldRaw": "5",
          "damage": 7,
          "knockbackGrowth": 50,
          "baseKnockback": 8,
          "setKnockback": 0,
          "angle": 70,
          "endlag": null
        },
        {
          "hitbox": "Level 3 Charge",
          "shieldSafety": {
            "isProjectile": true,
            "isStun": true,
            "min": 5,
            "max": 5
          },
          "shieldRaw": "5",
          "damage": 8,
          "knockbackGrowth": 50,
          "baseKnockback": 8,
          "setKnockback": 0,
          "angle": 70,
          "endlag": null
        },
        {
          "hitbox": "Level 4 Charge",
          "shieldSafety": {
            "isProjectile": true,
            "isStun": true,
            "min": 6,
            "max": 6
          },
          "shieldRaw": "6",
          "damage": 9,
          "knockbackGrowth": 50,
          "baseKnockback": 8,
          "setKnockback": 0,
          "angle": 70,
          "endlag": null
        },
        {
          "hitbox": "Level 5 Charge",
          "shieldSafety": {
            "isProjectile": true,
            "isStun": true,
            "min": 6,
            "max": 6
          },
          "shieldRaw": "6",
          "damage": 10,
          "knockbackGrowth": 50,
          "baseKnockback": 8,
          "setKnockback": 0,
          "angle": 70,
          "endlag": null
        },
        {
          "hitbox": "Level 6 Charge",
          "shieldSafety": {
            "isProjectile": true,
            "isStun": true,
            "min": 6,
            "max": 6
          },
          "shieldRaw": "6",
          "damage": 11,
          "knockbackGrowth": 50,
          "baseKnockback": 8,
          "setKnockback": 0,
          "angle": 70,
          "endlag": null
        },
        {
          "hitbox": "Level 7 Charge",
          "shieldSafety": {
            "isProjectile": true,
            "isStun": true,
            "min": 7,
            "max": 7
          },
          "shieldRaw": "7",
          "damage": 12,
          "knockbackGrowth": 50,
          "baseKnockback": 8,
          "setKnockback": 0,
          "angle": 70,
          "endlag": null
        },
        {
          "hitbox": "Level 8 Charge",
          "shieldSafety": {
            "isProjectile": true,
            "isStun": true,
            "min": 7,
            "max": 7
          },
          "shieldRaw": "7",
          "damage": 13,
          "knockbackGrowth": 50,
          "baseKnockback": 8,
          "setKnockback": 0,
          "angle": 70,
          "endlag": null
        },
        {
          "hitbox": "Level 9 Charge",
          "shieldSafety": {
            "isProjectile": true,
            "isStun": true,
            "min": 8,
            "max": 8
          },
          "shieldRaw": "8",
          "damage": 14,
          "knockbackGrowth": 50,
          "baseKnockback": 8,
          "setKnockback": 0,
          "angle": 70,
          "endlag": null
        },
        {
          "hitbox": "Fully Charge",
          "shieldSafety": {
            "isProjectile": true,
            "isStun": true,
            "min": 10,
            "max": 10
          },
          "shieldRaw": "10",
          "damage": 18,
          "knockbackGrowth": 50,
          "baseKnockback": 8,
          "setKnockback": 0,
          "angle": 70,
          "endlag": null
        }
      ]
    },
    {
      "move": "Side Special",
      "type": 4,
      "isUpSpecial": false,
      "startup": 27,
      "hitboxes": [
        {
          "hitbox": "Late",
          "shieldSafety": {
            "isProjectile": true,
            "isStun": true,
            "min": 4,
            "max": 4
          },
          "shieldRaw": "4",
          "damage": 6,
          "knockbackGrowth": 30,
          "baseKnockback": 55,
          "setKnockback": 0,
          "angle": 65,
          "endlag": null
        },
        {
          "hitbox": "Return",
          "shieldSafety": {
            "isProjectile": true,
            "isStun": true,
            "min": 3,
            "max": 3
          },
          "shieldRaw": "3",
          "damage": 3,
          "knockbackGrowth": 26,
          "baseKnockback": 25,
          "setKnockback": 0,
          "angle": 70,
          "endlag": null
        },
        {
          "hitbox": "Pointblank Frame1",
          "shieldSafety": {
            "isProjectile": true,
            "isStun": true,
            "min": 9,
            "max": 9
          },
          "shieldRaw": "9",
          "damage": 17,
          "knockbackGrowth": 30,
          "baseKnockback": 55,
          "setKnockback": 0,
          "angle": 70,
          "endlag": null
        },
        {
          "hitbox": "Pointblank Frame2",
          "shieldSafety": {
            "isProjectile": true,
            "isStun": true,
            "min": 9,
            "max": 9
          },
          "shieldRaw": "9",
          "damage": 17,
          "knockbackGrowth": 30,
          "baseKnockback": 55,
          "setKnockback": 0,
          "angle": 70,
          "endlag": null
        },
        {
          "hitbox": "Pointblank Frame3",
          "shieldSafety": {
            "isProjectile": true,
            "isStun": true,
            "min": 9,
            "max": 9
          },
          "shieldRaw": "9",
          "damage": 17,
          "knockbackGrowth": 30,
          "baseKnockback": 55,
          "setKnockback": 0,
          "angle": 70,
          "endlag": null
        },
        {
          "hitbox": "Pointblank Tilt Frame1",
          "shieldSafety": {
            "isProjectile": true,
            "isStun": true,
            "min": 8,
            "max": 8
          },
          "shieldRaw": "8",
          "damage": 15,
          "knockbackGrowth": 30,
          "baseKnockback": 55,
          "setKnockback": 0,
          "angle": 70,
          "endlag": null
        }
      ]
    },
    {
      "move": "Down Special",
      "type": 4,
      "isUpSpecial": false,
      "startup": 39,
      "hitboxes": [
        {
          "hitbox": "Explosion",
          "shieldSafety": {
            "isProjectile": true,
            "isStun": true,
            "min": 3,
            "max": 3
          },
          "shieldRaw": "3",
          "damage": 4,
          "knockbackGrowth": 60,
          "baseKnockback": 60,
          "setKnockback": 0,
          "angle": 70,
          "endlag": null
        },
        {
          "hitbox": "Grounded Dthrow",
          "shieldSafety": {
            "isProjectile": true,
            "isStun": true,
            "min": 5,
            "max": 5
          },
          "shieldRaw": "5",
          "damage": 8,
          "knockbackGrowth": 30,
          "baseKnockback": 60,
          "setKnockback": 0,
          "angle": 70,
          "endlag": null
        },
        {
          "hitbox": "Grounded Uthrow",
          "shieldSafety": {
            "isProjectile": true,
            "isStun": true,
            "min": 5,
            "max": 5
          },
          "shieldRaw": "5",
          "damage": 7,
          "knockbackGrowth": 30,
          "baseKnockback": 60,
          "setKnockback": 0,
          "angle": 70,
          "endlag": null
        },
        {
          "hitbox": "Grounded Fthrow",
          "shieldSafety": {
            "isProjectile": true,
            "isStun": true,
            "min": 4,
            "max": 4
          },
          "shieldRaw": "4",
          "damage": 6,
          "knockbackGrowth": 30,
          "baseKnockback": 60,
          "setKnockback": 0,
          "angle": 70,
          "endlag": null
        },
        {
          "hitbox": "Dash Throw",
          "shieldSafety": {
            "isProjectile": true,
            "isStun": true,
            "min": 4,
            "max": 4
          },
          "shieldRaw": "4",
          "damage": 6,
          "knockbackGrowth": 30,
          "baseKnockback": 60,
          "setKnockback": 0,
          "angle": 70,
          "endlag": null
        },
        {
          "hitbox": "Drop",
          "shieldSafety": {
            "isProjectile": true,
            "isStun": true,
            "min": 2,
            "max": 2
          },
          "shieldRaw": "2",
          "damage": 1,
          "knockbackGrowth": 30,
          "baseKnockback": 60,
          "setKnockback": 0,
          "angle": 70,
          "endlag": null
        },
        {
          "hitbox": "Release 19+",
          "shieldSafety": {
            "isProjectile": true,
            "isStun": true,
            "min": 2,
            "max": 2
          },
          "shieldRaw": "2",
          "damage": 1,
          "knockbackGrowth": 30,
          "baseKnockback": 60,
          "setKnockback": 0,
          "angle": 70,
          "endlag": null
        }
      ]
    },
    {
      "move": "Dash Attack",
      "type": 2,
      "isUpSpecial": false,
      "startup": 7,
      "hitboxes": [
        {
          "hitbox": "Id3",
          "shieldSafety": {
            "min": -27,
            "max": -27
          },
          "shieldRaw": "-27",
          "damage": 9,
          "knockbackGrowth": 100,
          "baseKnockback": 10,
          "setKnockback": 0,
          "angle": 90,
          "endlag": 28
        },
        {
          "hitbox": "Id0",
          "shieldSafety": {
            "min": -26,
            "max": -26
          },
          "shieldRaw": "-26",
          "damage": 12,
          "knockbackGrowth": 100,
          "baseKnockback": 10,
          "setKnockback": 0,
          "angle": 80,
          "endlag": 28
        },
        {
          "hitbox": "Id1",
          "shieldSafety": {
            "min": -27,
            "max": -27
          },
          "shieldRaw": "-27",
          "damage": 11,
          "knockbackGrowth": 100,
          "baseKnockback": 10,
          "setKnockback": 0,
          "angle": 70,
          "endlag": 28
        },
        {
          "hitbox": "Id2",
          "shieldSafety": {
            "min": -27,
            "max": -27
          },
          "shieldRaw": "-27",
          "damage": 11,
          "knockbackGrowth": 100,
          "baseKnockback": 10,
          "setKnockback": 0,
          "angle": 60,
          "endlag": 28
        }
      ]
    },
    {
      "move": "Forward Tilt",
      "type": 1,
      "isUpSpecial": false,
      "startup": 16,
      "hitboxes": [
        {
          "hitbox": "Id0",
          "shieldSafety": {
            "min": -15,
            "max": -15
          },
          "shieldRaw": "-15",
          "damage": 14,
          "knockbackGrowth": 90,
          "baseKnockback": 5,
          "setKnockback": 0,
          "angle": 361,
          "endlag": 20
        },
        {
          "hitbox": "Id1",
          "shieldSafety": {
            "min": -15,
            "max": -15
          },
          "shieldRaw": "-15",
          "damage": 15,
          "knockbackGrowth": 90,
          "baseKnockback": 5,
          "setKnockback": 0,
          "angle": 361,
          "endlag": 20
        },
        {
          "hitbox": "Id2",
          "shieldSafety": {
            "min": -15,
            "max": -15
          },
          "shieldRaw": "-15",
          "damage": 14,
          "knockbackGrowth": 90,
          "baseKnockback": 2,
          "setKnockback": 0,
          "angle": 361,
          "endlag": 20
        },
        {
          "hitbox": "Id3",
          "shieldSafety": {
            "min": -16,
            "max": -16
          },
          "shieldRaw": "-16",
          "damage": 13,
          "knockbackGrowth": 90,
          "baseKnockback": 2,
          "setKnockback": 0,
          "angle": 361,
          "endlag": 20
        }
      ]
    },
    {
      "move": "Up Tilt",
      "type": 1,
      "isUpSpecial": false,
      "startup": 9,
      "hitboxes": [
        {
          "hitbox": "Id0",
          "shieldSafety": {
            "min": -14,
            "max": -14
          },
          "shieldRaw": "-14",
          "damage": 9,
          "knockbackGrowth": 122,
          "baseKnockback": 30,
          "setKnockback": 0,
          "angle": 95,
          "endlag": 14
        },
        {
          "hitbox": "Id1",
          "shieldSafety": {
            "min": -14,
            "max": -14
          },
          "shieldRaw": "-14",
          "damage": 9,
          "knockbackGrowth": 130,
          "baseKnockback": 30,
          "setKnockback": 0,
          "angle": 85,
          "endlag": 14
        },
        {
          "hitbox": "Id2",
          "shieldSafety": {
            "min": -14,
            "max": -14
          },
          "shieldRaw": "-14",
          "damage": 9,
          "knockbackGrowth": 124,
          "baseKnockback": 30,
          "setKnockback": 0,
          "angle": 85,
          "endlag": 14
        },
        {
          "hitbox": "Id3",
          "shieldSafety": {
            "min": -14,
            "max": -14
          },
          "shieldRaw": "-14",
          "damage": 9,
          "knockbackGrowth": 123,
          "baseKnockback": 30,
          "setKnockback": 0,
          "angle": 85,
          "endlag": 14
        }
      ]
    },
    {
      "move": "Down Tilt",
      "type": 1,
      "isUpSpecial": false,
      "startup": 14,
      "hitboxes": [
        {
          "hitbox": "Id0",
          "shieldSafety": {
            "min": -10,
            "max": -10
          },
          "shieldRaw": "-10",
          "damage": 11,
          "knockbackGrowth": 50,
          "baseKnockback": 80,
          "setKnockback": 0,
          "angle": 80,
          "endlag": 14
        },
        {
          "hitbox": "Id1",
          "shieldSafety": {
            "min": -10,
            "max": -10
          },
          "shieldRaw": "-10",
          "damage": 11,
          "knockbackGrowth": 50,
          "baseKnockback": 80,
          "setKnockback": 0,
          "angle": 280,
          "endlag": 14
        },
        {
          "hitbox": "Id2",
          "shieldSafety": {
            "min": -10,
            "max": -10
          },
          "shieldRaw": "-10",
          "damage": 11,
          "knockbackGrowth": 50,
          "baseKnockback": 80,
          "setKnockback": 0,
          "angle": 280,
          "endlag": 14
        },
        {
          "hitbox": "Id3",
          "shieldSafety": {
            "min": -10,
            "max": -10
          },
          "shieldRaw": "-10",
          "damage": 11,
          "knockbackGrowth": 50,
          "baseKnockback": 80,
          "setKnockback": 0,
          "angle": 280,
          "endlag": 14
        }
      ]
    },
    {
      "move": "Forward Smash",
      "type": 2,
      "isUpSpecial": false,
      "startup": 15,
      "hitboxes": [
        {
          "hitbox": "Id0",
          "shieldSafety": {
            "min": -27,
            "max": -27
          },
          "shieldRaw": "-27",
          "damage": 13,
          "knockbackGrowth": 83,
          "baseKnockback": 30,
          "setKnockback": 0,
          "angle": 361,
          "endlag": 31
        },
        {
          "hitbox": "Id1",
          "shieldSafety": {
            "min": -26,
            "max": -26
          },
          "shieldRaw": "-26",
          "damage": 14,
          "knockbackGrowth": 85,
          "baseKnockback": 30,
          "setKnockback": 0,
          "angle": 361,
          "endlag": 31
        },
        {
          "hitbox": "Id2",
          "shieldSafety": {
            "min": -26,
            "max": -26
          },
          "shieldRaw": "-26",
          "damage": 14,
          "knockbackGrowth": 85,
          "baseKnockback": 30,
          "setKnockback": 0,
          "angle": 361,
          "endlag": 31
        },
        {
          "hitbox": "Id3",
          "shieldSafety": {
            "min": -26,
            "max": -26
          },
          "shieldRaw": "-26",
          "damage": 14,
          "knockbackGrowth": 85,
          "baseKnockback": 30,
          "setKnockback": 0,
          "angle": 361,
          "endlag": 31
        }
      ]
    },
    {
      "move": "Up Smash",
      "type": 2,
      "isUpSpecial": false,
      "startup": 11,
      "hitboxes": [
        {
          "hitbox": "Id0",
          "shieldSafety": {
            "min": -38,
            "max": -38
          },
          "shieldRaw": "-38",
          "damage": 4,
          "knockbackGrowth": 100,
          "baseKnockback": 40,
          "setKnockback": 26,
          "angle": 98,
          "endlag": 37
        },
        {
          "hitbox": "Id1",
          "shieldSafety": {
            "min": -38,
            "max": -38
          },
          "shieldRaw": "-38",
          "damage": 4,
          "knockbackGrowth": 100,
          "baseKnockback": 40,
          "setKnockback": 30,
          "angle": 98,
          "endlag": 37
        },
        {
          "hitbox": "Id2",
          "shieldSafety": {
            "min": -38,
            "max": -38
          },
          "shieldRaw": "-38",
          "damage": 4,
          "knockbackGrowth": 100,
          "baseKnockback": 40,
          "setKnockback": 33,
          "angle": 98,
          "endlag": 37
        },
        {
          "hitbox": "Id3",
          "shieldSafety": {
            "min": -38,
            "max": -38
          },
          "shieldRaw": "-38",
          "damage": 4,
          "knockbackGrowth": 100,
          "baseKnockback": 40,
          "setKnockback": 33,
          "angle": 98,
          "endlag": 37
        },
        {
          "hitbox": "Id0",
          "shieldSafety": {
            "min": -24,
            "max": -24
          },
          "shieldRaw": "-24",
          "damage": 2,
          "knockbackGrowth": 100,
          "baseKnockback": 0,
          "setKnockback": 30,
          "angle": 90,
          "endlag": 24
        },
        {
          "hitbox": "Id1",
          "shieldSafety": {
            "min": -24,
            "max": -24
          },
          "shieldRaw": "-24",
          "damage": 2,
          "knockbackGrowth": 100,
          "baseKnockback": 0,
          "setKnockback": 33,
          "angle": 90,
          "endlag": 24
        },
        {
          "hitbox": "Id2",
          "shieldSafety": {
            "min": -24,
            "max": -24
          },
          "shieldRaw": "-24",
          "damage": 2,
          "knockbackGrowth": 100,
          "baseKnockback": 0,
          "setKnockback": 37,
          "angle": 90,
          "endlag": 24
        },
        {
          "hitbox": "Id3",
          "shieldSafety": {
            "min": -24,
            "max": -24
          },
          "shieldRaw": "-24",
          "damage": 2,
          "knockbackGrowth": 100,
          "baseKnockback": 0,
          "setKnockback": 40,
          "angle": 90,
          "endlag": 24
        },
        {
          "hitbox": "Id0",
          "shieldSafety": {
            "min": -5,
            "max": -5
          },
          "shieldRaw": "-5",
          "damage": 10,
          "knockbackGrowth": 80,
          "baseKnockback": 90,
          "setKnockback": 0,
          "angle": 80,
          "endlag": 9
        },
        {
          "hitbox": "Id1",
          "shieldSafety": {
            "min": -5,
            "max": -5
          },
          "shieldRaw": "-5",
          "damage": 10,
          "knockbackGrowth": 80,
          "baseKnockback": 90,
          "setKnockback": 0,
          "angle": 90,
          "endlag": 9
        },
        {
          "hitbox": "Id2",
          "shieldSafety": {
            "min": -5,
            "max": -5
          },
          "shieldRaw": "-5",
          "damage": 9,
          "knockbackGrowth": 80,
          "baseKnockback": 90,
          "setKnockback": 0,
          "angle": 90,
          "endlag": 9
        },
        {
          "hitbox": "Id3",
          "shieldSafety": {
            "min": -5,
            "max": -5
          },
          "shieldRaw": "-5",
          "damage": 9,
          "knockbackGrowth": 80,
          "baseKnockback": 90,
          "setKnockback": 0,
          "angle": 90,
          "endlag": 9
        }
      ]
    },
    {
      "move": "Down Smash",
      "type": 2,
      "isUpSpecial": false,
      "startup": 9,
      "hitboxes": [
        {
          "hitbox": "Id0",
          "shieldSafety": {
            "min": -26,
            "max": -26
          },
          "shieldRaw": "-26",
          "damage": 13,
          "knockbackGrowth": 90,
          "baseKnockback": 26,
          "setKnockback": 0,
          "angle": 75,
          "endlag": 31
        },
        {
          "hitbox": "Id1",
          "shieldSafety": {
            "min": -24,
            "max": -24
          },
          "shieldRaw": "-24",
          "damage": 16,
          "knockbackGrowth": 90,
          "baseKnockback": 26,
          "setKnockback": 0,
          "angle": 75,
          "endlag": 31
        },
        {
          "hitbox": "Id2",
          "shieldSafety": {
            "min": -24,
            "max": -24
          },
          "shieldRaw": "-24",
          "damage": 17,
          "knockbackGrowth": 90,
          "baseKnockback": 26,
          "setKnockback": 0,
          "angle": 75,
          "endlag": 31
        },
        {
          "hitbox": "Id3",
          "shieldSafety": {
            "min": -24,
            "max": -24
          },
          "shieldRaw": "-24",
          "damage": 16,
          "knockbackGrowth": 90,
          "baseKnockback": 26,
          "setKnockback": 0,
          "angle": 75,
          "endlag": 31
        },
        {
          "hitbox": "Id0",
          "shieldSafety": {
            "min": -15,
            "max": -15
          },
          "shieldRaw": "-15",
          "damage": 11,
          "knockbackGrowth": 90,
          "baseKnockback": 20,
          "setKnockback": 0,
          "angle": 75,
          "endlag": 19
        },
        {
          "hitbox": "Id1",
          "shieldSafety": {
            "min": -12,
            "max": -12
          },
          "shieldRaw": "-12",
          "damage": 16,
          "knockbackGrowth": 90,
          "baseKnockback": 20,
          "setKnockback": 0,
          "angle": 75,
          "endlag": 19
        },
        {
          "hitbox": "Id2",
          "shieldSafety": {
            "min": -12,
            "max": -12
          },
          "shieldRaw": "-12",
          "damage": 17,
          "knockbackGrowth": 90,
          "baseKnockback": 20,
          "setKnockback": 0,
          "angle": 75,
          "endlag": 19
        },
        {
          "hitbox": "Id3",
          "shieldSafety": {
            "min": -12,
            "max": -12
          },
          "shieldRaw": "-12",
          "damage": 16,
          "knockbackGrowth": 90,
          "baseKnockback": 20,
          "setKnockback": 0,
          "angle": 75,
          "endlag": 19
        }
      ]
    },
    {
      "move": "Neutral Air",
      "type": 3,
      "isUpSpecial": false,
      "startup": 4,
      "hitboxes": [
        {
          "hitbox": "Id0",
          "shieldSafety": {
            "min": -9,
            "max": -1
          },
          "shieldRaw": "-9/-1",
          "damage": 9,
          "knockbackGrowth": 100,
          "baseKnockback": 15,
          "setKnockback": 0,
          "angle": 361,
          "endlag": 7
        },
        {
          "hitbox": "Id1",
          "shieldSafety": {
            "min": -9,
            "max": -1
          },
          "shieldRaw": "-9/-1",
          "damage": 11,
          "knockbackGrowth": 100,
          "baseKnockback": 15,
          "setKnockback": 0,
          "angle": 361,
          "endlag": 7
        },
        {
          "hitbox": "Id2",
          "shieldSafety": {
            "min": -10,
            "max": -2
          },
          "shieldRaw": "-10/-2",
          "damage": 8,
          "knockbackGrowth": 100,
          "baseKnockback": 15,
          "setKnockback": 0,
          "angle": 361,
          "endlag": 7
        }
      ]
    },
    {
      "move": "Back Air",
      "type": 3,
      "isUpSpecial": false,
      "startup": 6,
      "hitboxes": [
        {
          "hitbox": "Hit 1",
          "shieldSafety": {
            "min": -10,
            "max": -2
          },
          "shieldRaw": "-10/-2",
          "damage": 7,
          "knockbackGrowth": 100,
          "baseKnockback": 0,
          "setKnockback": 0,
          "angle": 361,
          "endlag": 7
        },
        {
          "hitbox": "Hit 1",
          "shieldSafety": {
            "min": -10,
            "max": -2
          },
          "shieldRaw": "-10/-2",
          "damage": 7,
          "knockbackGrowth": 100,
          "baseKnockback": 0,
          "setKnockback": 0,
          "angle": 361,
          "endlag": 7
        },
        {
          "hitbox": "Hit 1",
          "shieldSafety": {
            "min": -10,
            "max": -2
          },
          "shieldRaw": "-10/-2",
          "damage": 7,
          "knockbackGrowth": 100,
          "baseKnockback": 0,
          "setKnockback": 0,
          "angle": 361,
          "endlag": 7
        },
        {
          "hitbox": "Hit 2",
          "shieldSafety": {
            "min": -10,
            "max": -2
          },
          "shieldRaw": "-10/-2",
          "damage": 7,
          "knockbackGrowth": 100,
          "baseKnockback": 15,
          "setKnockback": 0,
          "angle": 361,
          "endlag": 7
        },
        {
          "hitbox": "Hit 2",
          "shieldSafety": {
            "min": -10,
            "max": -2
          },
          "shieldRaw": "-10/-2",
          "damage": 7,
          "knockbackGrowth": 100,
          "baseKnockback": 15,
          "setKnockback": 0,
          "angle": 361,
          "endlag": 7
        },
        {
          "hitbox": "Hit 2",
          "shieldSafety": {
            "min": -10,
            "max": -2
          },
          "shieldRaw": "-10/-2",
          "damage": 7,
          "knockbackGrowth": 100,
          "baseKnockback": 15,
          "setKnockback": 0,
          "angle": 361,
          "endlag": 7
        }
      ]
    },
    {
      "move": "Jab 1",
      "type": 2,
      "isUpSpecial": false,
      "startup": 6,
      "hitboxes": [
        {
          "hitbox": "Id0",
          "shieldSafety": {
            "min": -10,
            "max": -10
          },
          "shieldRaw": "-10",
          "damage": 5,
          "knockbackGrowth": 60,
          "baseKnockback": 10,
          "setKnockback": 0,
          "angle": 361,
          "endlag": 12
        },
        {
          "hitbox": "Id1",
          "shieldSafety": {
            "min": -10,
            "max": -10
          },
          "shieldRaw": "-10",
          "damage": 5,
          "knockbackGrowth": 60,
          "baseKnockback": 10,
          "setKnockback": 0,
          "angle": 361,
          "endlag": 12
        },
        {
          "hitbox": "Id2",
          "shieldSafety": {
            "min": -10,
            "max": -10
          },
          "shieldRaw": "-10",
          "damage": 5,
          "knockbackGrowth": 60,
          "baseKnockback": 10,
          "setKnockback": 0,
          "angle": 361,
          "endlag": 12
        },
        {
          "hitbox": "Id3",
          "shieldSafety": {
            "min": -10,
            "max": -10
          },
          "shieldRaw": "-10",
          "damage": 5,
          "knockbackGrowth": 60,
          "baseKnockback": 10,
          "setKnockback": 0,
          "angle": 361,
          "endlag": 12
        }
      ]
    },
    {
      "move": "Jab 2",
      "type": 2,
      "isUpSpecial": false,
      "startup": 6,
      "hitboxes": [
        {
          "hitbox": "Id0",
          "shieldSafety": {
            "min": -8,
            "max": -8
          },
          "shieldRaw": "-8",
          "damage": 3,
          "knockbackGrowth": 60,
          "baseKnockback": 10,
          "setKnockback": 0,
          "angle": 361,
          "endlag": 10
        },
        {
          "hitbox": "Id1",
          "shieldSafety": {
            "min": -8,
            "max": -8
          },
          "shieldRaw": "-8",
          "damage": 3,
          "knockbackGrowth": 60,
          "baseKnockback": 10,
          "setKnockback": 0,
          "angle": 361,
          "endlag": 10
        },
        {
          "hitbox": "Id2",
          "shieldSafety": {
            "min": -8,
            "max": -8
          },
          "shieldRaw": "-8",
          "damage": 3,
          "knockbackGrowth": 60,
          "baseKnockback": 10,
          "setKnockback": 0,
          "angle": 361,
          "endlag": 10
        },
        {
          "hitbox": "Id3",
          "shieldSafety": {
            "min": -8,
            "max": -8
          },
          "shieldRaw": "-8",
          "damage": 3,
          "knockbackGrowth": 60,
          "baseKnockback": 10,
          "setKnockback": 0,
          "angle": 361,
          "endlag": 10
        }
      ]
    },
    {
      "move": "Jab 3",
      "type": 2,
      "isUpSpecial": false,
      "startup": 6,
      "hitboxes": [
        {
          "hitbox": "Id0",
          "shieldSafety": {
            "min": -22,
            "max": -22
          },
          "shieldRaw": "-22",
          "damage": 6,
          "knockbackGrowth": 100,
          "baseKnockback": 10,
          "setKnockback": 0,
          "angle": 361,
          "endlag": 22
        },
        {
          "hitbox": "Id1",
          "shieldSafety": {
            "min": -22,
            "max": -22
          },
          "shieldRaw": "-22",
          "damage": 6,
          "knockbackGrowth": 100,
          "baseKnockback": 10,
          "setKnockback": 0,
          "angle": 361,
          "endlag": 22
        },
        {
          "hitbox": "Id2",
          "shieldSafety": {
            "min": -22,
            "max": -22
          },
          "shieldRaw": "-22",
          "damage": 6,
          "knockbackGrowth": 100,
          "baseKnockback": 10,
          "setKnockback": 0,
          "angle": 361,
          "endlag": 22
        },
        {
          "hitbox": "Id3",
          "shieldSafety": {
            "min": -22,
            "max": -22
          },
          "shieldRaw": "-22",
          "damage": 6,
          "knockbackGrowth": 100,
          "baseKnockback": 10,
          "setKnockback": 0,
          "angle": 361,
          "endlag": 22
        }
      ]
    },
    {
      "move": "Rapid Jabs",
      "type": 2,
      "isUpSpecial": false,
      "startup": 9,
      "hitboxes": [
        {
          "hitbox": "Id0",
          "shieldSafety": {
            "min": -30,
            "max": -30
          },
          "shieldRaw": "-30",
          "damage": 1,
          "knockbackGrowth": 40,
          "baseKnockback": 15,
          "setKnockback": 0,
          "angle": 0,
          "endlag": 31
        },
        {
          "hitbox": "Id1",
          "shieldSafety": {
            "min": -30,
            "max": -30
          },
          "shieldRaw": "-30",
          "damage": 1,
          "knockbackGrowth": 50,
          "baseKnockback": 15,
          "setKnockback": 0,
          "angle": 0,
          "endlag": 31
        },
        {
          "hitbox": "Id2",
          "shieldSafety": {
            "min": -30,
            "max": -30
          },
          "shieldRaw": "-30",
          "damage": 1,
          "knockbackGrowth": 60,
          "baseKnockback": 15,
          "setKnockback": 0,
          "angle": 0,
          "endlag": 31
        },
        {
          "hitbox": "Id3",
          "shieldSafety": {
            "min": -30,
            "max": -30
          },
          "shieldRaw": "-30",
          "damage": 1,
          "knockbackGrowth": 60,
          "baseKnockback": 15,
          "setKnockback": 0,
          "angle": 0,
          "endlag": 31
        }
      ]
    },
    {
      "move": "Up Special (Air)",
      "type": 4,
      "isUpSpecial": true,
      "startup": 8,
      "hitboxes": [
        {
          "hitbox": "Hit 1 (Aerial)",
          "shieldSafety": {
            "min": -76,
            "max": -76
          },
          "shieldRaw": "-76",
          "damage": 4,
          "knockbackGrowth": 100,
          "baseKnockback": 0,
          "setKnockback": 72,
          "angle": 90,
          "endlag": 79
        },
        {
          "hitbox": "Hit 1 (Aerial)",
          "shieldSafety": {
            "min": -75,
            "max": -75
          },
          "shieldRaw": "-75",
          "damage": 6,
          "knockbackGrowth": 100,
          "baseKnockback": 0,
          "setKnockback": 68,
          "angle": 86,
          "endlag": 79
        },
        {
          "hitbox": "Hit 1 (Aerial)",
          "shieldSafety": {
            "min": -75,
            "max": -75
          },
          "shieldRaw": "-75",
          "damage": 6,
          "knockbackGrowth": 100,
          "baseKnockback": 0,
          "setKnockback": 68,
          "angle": 80,
          "endlag": 79
        },
        {
          "hitbox": "Hit 1 (Aerial)",
          "shieldSafety": {
            "min": -75,
            "max": -75
          },
          "shieldRaw": "-75",
          "damage": 6,
          "knockbackGrowth": 100,
          "baseKnockback": 0,
          "setKnockback": 68,
          "angle": 75,
          "endlag": 79
        },
        {
          "hitbox": "Hit 2 (Aerial)",
          "shieldSafety": {
            "min": -77,
            "max": -77
          },
          "shieldRaw": "-77",
          "damage": 2,
          "knockbackGrowth": 100,
          "baseKnockback": 0,
          "setKnockback": 64,
          "angle": 90,
          "endlag": 79
        },
        {
          "hitbox": "Hit 2 (Aerial)",
          "shieldSafety": {
            "min": -77,
            "max": -77
          },
          "shieldRaw": "-77",
          "damage": 2,
          "knockbackGrowth": 100,
          "baseKnockback": 0,
          "setKnockback": 60,
          "angle": 86,
          "endlag": 79
        },
        {
          "hitbox": "Hit 2 (Aerial)",
          "shieldSafety": {
            "min": -77,
            "max": -77
          },
          "shieldRaw": "-77",
          "damage": 2,
          "knockbackGrowth": 100,
          "baseKnockback": 0,
          "setKnockback": 60,
          "angle": 80,
          "endlag": 79
        },
        {
          "hitbox": "Hit 2 (Aerial)",
          "shieldSafety": {
            "min": -77,
            "max": -77
          },
          "shieldRaw": "-77",
          "damage": 2,
          "knockbackGrowth": 100,
          "baseKnockback": 0,
          "setKnockback": 60,
          "angle": 75,
          "endlag": 79
        },
        {
          "hitbox": "Hit 3 (Aerial)",
          "shieldSafety": {
            "min": -77,
            "max": -77
          },
          "shieldRaw": "-77",
          "damage": 2,
          "knockbackGrowth": 100,
          "baseKnockback": 0,
          "setKnockback": 58,
          "angle": 90,
          "endlag": 79
        },
        {
          "hitbox": "Hit 3 (Aerial)",
          "shieldSafety": {
            "min": -77,
            "max": -77
          },
          "shieldRaw": "-77",
          "damage": 2,
          "knockbackGrowth": 100,
          "baseKnockback": 0,
          "setKnockback": 55,
          "angle": 86,
          "endlag": 79
        },
        {
          "hitbox": "Hit 3 (Aerial)",
          "shieldSafety": {
            "min": -77,
            "max": -77
          },
          "shieldRaw": "-77",
          "damage": 2,
          "knockbackGrowth": 100,
          "baseKnockback": 0,
          "setKnockback": 55,
          "angle": 80,
          "endlag": 79
        },
        {
          "hitbox": "Hit 3 (Aerial)",
          "shieldSafety": {
            "min": -77,
            "max": -77
          },
          "shieldRaw": "-77",
          "damage": 2,
          "knockbackGrowth": 100,
          "baseKnockback": 0,
          "setKnockback": 55,
          "angle": 75,
          "endlag": 79
        },
        {
          "hitbox": "Hit 4 (Aerial)",
          "shieldSafety": {
            "min": -77,
            "max": -77
          },
          "shieldRaw": "-77",
          "damage": 2,
          "knockbackGrowth": 100,
          "baseKnockback": 0,
          "setKnockback": 46,
          "angle": 90,
          "endlag": 79
        },
        {
          "hitbox": "Hit 4 (Aerial)",
          "shieldSafety": {
            "min": -77,
            "max": -77
          },
          "shieldRaw": "-77",
          "damage": 2,
          "knockbackGrowth": 100,
          "baseKnockback": 0,
          "setKnockback": 43,
          "angle": 86,
          "endlag": 79
        },
        {
          "hitbox": "Hit 4 (Aerial)",
          "shieldSafety": {
            "min": -77,
            "max": -77
          },
          "shieldRaw": "-77",
          "damage": 2,
          "knockbackGrowth": 100,
          "baseKnockback": 0,
          "setKnockback": 43,
          "angle": 80,
          "endlag": 79
        },
        {
          "hitbox": "Hit 4 (Aerial)",
          "shieldSafety": {
            "min": -77,
            "max": -77
          },
          "shieldRaw": "-77",
          "damage": 2,
          "knockbackGrowth": 100,
          "baseKnockback": 0,
          "setKnockback": 43,
          "angle": 75,
          "endlag": 79
        },
        {
          "hitbox": "Hit 5 (Aerial)",
          "shieldSafety": {
            "min": -76,
            "max": -76
          },
          "shieldRaw": "-76",
          "damage": 4,
          "knockbackGrowth": 160,
          "baseKnockback": 40,
          "setKnockback": 0,
          "angle": 361,
          "endlag": 79
        },
        {
          "hitbox": "Hit 5 (Aerial)",
          "shieldSafety": {
            "min": -75,
            "max": -75
          },
          "shieldRaw": "-75",
          "damage": 6,
          "knockbackGrowth": 160,
          "baseKnockback": 40,
          "setKnockback": 0,
          "angle": 361,
          "endlag": 79
        },
        {
          "hitbox": "Hit 5 (Aerial)",
          "shieldSafety": {
            "min": -75,
            "max": -75
          },
          "shieldRaw": "-75",
          "damage": 6,
          "knockbackGrowth": 160,
          "baseKnockback": 40,
          "setKnockback": 0,
          "angle": 361,
          "endlag": 79
        },
        {
          "hitbox": "Hit 5 (Aerial)",
          "shieldSafety": {
            "min": -75,
            "max": -75
          },
          "shieldRaw": "-75",
          "damage": 6,
          "knockbackGrowth": 160,
          "baseKnockback": 40,
          "setKnockback": 0,
          "angle": 361,
          "endlag": 79
        }
      ]
    },
    {
      "move": "Grab",
      "type": 6,
      "isUpSpecial": false,
      "startup": 11,
      "hitboxes": [
        {
          "hitbox": "Id0",
          "shieldSafety": {
            "min": -73,
            "max": -73
          },
          "shieldRaw": "-73",
          "damage": 0,
          "knockbackGrowth": 100,
          "baseKnockback": 0,
          "setKnockback": 0,
          "angle": 361,
          "endlag": 72
        },
        {
          "hitbox": "Id1",
          "shieldSafety": {
            "min": -73,
            "max": -73
          },
          "shieldRaw": "-73",
          "damage": 0,
          "knockbackGrowth": 100,
          "baseKnockback": 0,
          "setKnockback": 0,
          "angle": 361,
          "endlag": 72
        },
        {
          "hitbox": "Id2",
          "shieldSafety": {
            "min": -73,
            "max": -73
          },
          "shieldRaw": "-73",
          "damage": 0,
          "knockbackGrowth": 100,
          "baseKnockback": 0,
          "setKnockback": 0,
          "angle": 361,
          "endlag": 72
        },
        {
          "hitbox": "Id0",
          "shieldSafety": {
            "min": -73,
            "max": -73
          },
          "shieldRaw": "-73",
          "damage": 0,
          "knockbackGrowth": 100,
          "baseKnockback": 0,
          "setKnockback": 0,
          "angle": 361,
          "endlag": 68
        }
      ]
    },
    {
      "move": "Dashgrab",
      "type": 6,
      "isUpSpecial": false,
      "startup": 12,
      "hitboxes": [
        {
          "hitbox": "Id0",
          "shieldSafety": {
            "min": -82,
            "max": -82
          },
          "shieldRaw": "-82",
          "damage": 0,
          "knockbackGrowth": 100,
          "baseKnockback": 0,
          "setKnockback": 0,
          "angle": 361,
          "endlag": 83
        },
        {
          "hitbox": "Id1",
          "shieldSafety": {
            "min": -82,
            "max": -82
          },
          "shieldRaw": "-82",
          "damage": 0,
          "knockbackGrowth": 100,
          "baseKnockback": 0,
          "setKnockback": 0,
          "angle": 361,
          "endlag": 83
        },
        {
          "hitbox": "Id0",
          "shieldSafety": {
            "min": -82,
            "max": -82
          },
          "shieldRaw": "-82",
          "damage": 0,
          "knockbackGrowth": 100,
          "baseKnockback": 0,
          "setKnockback": 0,
          "angle": 361,
          "endlag": 78
        }
      ]
    },
    {
      "move": "Getup-Attack (Stomach)",
      "type": 7,
      "isUpSpecial": false,
      "startup": null,
      "hitboxes": [
        {
          "hitbox": "Hit 1 (Back)",
          "shieldSafety": {
            "min": -45,
            "max": -45
          },
          "shieldRaw": "-45",
          "damage": 6,
          "knockbackGrowth": 50,
          "baseKnockback": 80,
          "setKnockback": 0,
          "angle": 361,
          "endlag": 49
        },
        {
          "hitbox": "Hit 1 (Back)",
          "shieldSafety": {
            "min": -45,
            "max": -45
          },
          "shieldRaw": "-45",
          "damage": 6,
          "knockbackGrowth": 50,
          "baseKnockback": 80,
          "setKnockback": 0,
          "angle": 361,
          "endlag": 49
        },
        {
          "hitbox": "Hit 1 (Back)",
          "shieldSafety": {
            "min": -45,
            "max": -45
          },
          "shieldRaw": "-45",
          "damage": 6,
          "knockbackGrowth": 50,
          "baseKnockback": 80,
          "setKnockback": 0,
          "angle": 361,
          "endlag": 49
        },
        {
          "hitbox": "Hit 1 (Back)",
          "shieldSafety": {
            "min": -45,
            "max": -45
          },
          "shieldRaw": "-45",
          "damage": 6,
          "knockbackGrowth": 50,
          "baseKnockback": 80,
          "setKnockback": 0,
          "angle": 361,
          "endlag": 49
        },
        {
          "hitbox": "Hit 2 (Back)",
          "shieldSafety": {
            "min": -45,
            "max": -45
          },
          "shieldRaw": "-45",
          "damage": 6,
          "knockbackGrowth": 50,
          "baseKnockback": 80,
          "setKnockback": 0,
          "angle": 361,
          "endlag": 49
        },
        {
          "hitbox": "Hit 2 (Back)",
          "shieldSafety": {
            "min": -45,
            "max": -45
          },
          "shieldRaw": "-45",
          "damage": 6,
          "knockbackGrowth": 50,
          "baseKnockback": 80,
          "setKnockback": 0,
          "angle": 361,
          "endlag": 49
        },
        {
          "hitbox": "Hit 2 (Back)",
          "shieldSafety": {
            "min": -45,
            "max": -45
          },
          "shieldRaw": "-45",
          "damage": 6,
          "knockbackGrowth": 50,
          "baseKnockback": 80,
          "setKnockback": 0,
          "angle": 361,
          "endlag": 49
        },
        {
          "hitbox": "Hit 2 (Back)",
          "shieldSafety": {
            "min": -45,
            "max": -45
          },
          "shieldRaw": "-45",
          "damage": 6,
          "knockbackGrowth": 50,
          "baseKnockback": 80,
          "setKnockback": 0,
          "angle": 361,
          "endlag": 49
        },
        {
          "hitbox": "Hit 1 (Front)",
          "shieldSafety": {
            "min": -45,
            "max": -45
          },
          "shieldRaw": "-45",
          "damage": 6,
          "knockbackGrowth": 50,
          "baseKnockback": 80,
          "setKnockback": 0,
          "angle": 361,
          "endlag": 49
        },
        {
          "hitbox": "Hit 1 (Front)",
          "shieldSafety": {
            "min": -45,
            "max": -45
          },
          "shieldRaw": "-45",
          "damage": 6,
          "knockbackGrowth": 50,
          "baseKnockback": 80,
          "setKnockback": 0,
          "angle": 361,
          "endlag": 49
        },
        {
          "hitbox": "Hit 1 (Front)",
          "shieldSafety": {
            "min": -45,
            "max": -45
          },
          "shieldRaw": "-45",
          "damage": 6,
          "knockbackGrowth": 50,
          "baseKnockback": 80,
          "setKnockback": 0,
          "angle": 361,
          "endlag": 49
        },
        {
          "hitbox": "Hit 1 (Front)",
          "shieldSafety": {
            "min": -45,
            "max": -45
          },
          "shieldRaw": "-45",
          "damage": 6,
          "knockbackGrowth": 50,
          "baseKnockback": 80,
          "setKnockback": 0,
          "angle": 361,
          "endlag": 49
        },
        {
          "hitbox": "Hit 2 (Front)",
          "shieldSafety": {
            "min": -45,
            "max": -45
          },
          "shieldRaw": "-45",
          "damage": 6,
          "knockbackGrowth": 50,
          "baseKnockback": 80,
          "setKnockback": 0,
          "angle": 361,
          "endlag": 49
        },
        {
          "hitbox": "Hit 2 (Front)",
          "shieldSafety": {
            "min": -45,
            "max": -45
          },
          "shieldRaw": "-45",
          "damage": 6,
          "knockbackGrowth": 50,
          "baseKnockback": 80,
          "setKnockback": 0,
          "angle": 361,
          "endlag": 49
        },
        {
          "hitbox": "Hit 2 (Front)",
          "shieldSafety": {
            "min": -45,
            "max": -45
          },
          "shieldRaw": "-45",
          "damage": 6,
          "knockbackGrowth": 50,
          "baseKnockback": 80,
          "setKnockback": 0,
          "angle": 361,
          "endlag": 49
        },
        {
          "hitbox": "Hit 2 (Front)",
          "shieldSafety": {
            "min": -45,
            "max": -45
          },
          "shieldRaw": "-45",
          "damage": 6,
          "knockbackGrowth": 50,
          "baseKnockback": 80,
          "setKnockback": 0,
          "angle": 361,
          "endlag": 49
        }
      ]
    },
    {
      "move": "Side Special (Air)",
      "type": 4,
      "isUpSpecial": false,
      "startup": 27,
      "hitboxes": [
        {
          "hitbox": "Late",
          "shieldSafety": {
            "isProjectile": true,
            "isStun": true,
            "min": 4,
            "max": 4
          },
          "shieldRaw": "4",
          "damage": 6,
          "knockbackGrowth": 30,
          "baseKnockback": 55,
          "setKnockback": 0,
          "angle": 65,
          "endlag": null
        },
        {
          "hitbox": "Return",
          "shieldSafety": {
            "isProjectile": true,
            "isStun": true,
            "min": 3,
            "max": 3
          },
          "shieldRaw": "3",
          "damage": 3,
          "knockbackGrowth": 26,
          "baseKnockback": 25,
          "setKnockback": 0,
          "angle": 70,
          "endlag": null
        },
        {
          "hitbox": "Pointblank Frame1",
          "shieldSafety": {
            "isProjectile": true,
            "isStun": true,
            "min": 9,
            "max": 9
          },
          "shieldRaw": "9",
          "damage": 17,
          "knockbackGrowth": 30,
          "baseKnockback": 55,
          "setKnockback": 0,
          "angle": 70,
          "endlag": null
        },
        {
          "hitbox": "Pointblank Frame2",
          "shieldSafety": {
            "isProjectile": true,
            "isStun": true,
            "min": 9,
            "max": 9
          },
          "shieldRaw": "9",
          "damage": 17,
          "knockbackGrowth": 30,
          "baseKnockback": 55,
          "setKnockback": 0,
          "angle": 70,
          "endlag": null
        },
        {
          "hitbox": "Pointblank Frame3",
          "shieldSafety": {
            "isProjectile": true,
            "isStun": true,
            "min": 9,
            "max": 9
          },
          "shieldRaw": "9",
          "damage": 17,
          "knockbackGrowth": 30,
          "baseKnockback": 55,
          "setKnockback": 0,
          "angle": 70,
          "endlag": null
        },
        {
          "hitbox": "Pointblank Tilt Frame1",
          "shieldSafety": {
            "isProjectile": true,
            "isStun": true,
            "min": 8,
            "max": 8
          },
          "shieldRaw": "8",
          "damage": 15,
          "knockbackGrowth": 30,
          "baseKnockback": 55,
          "setKnockback": 0,
          "angle": 70,
          "endlag": null
        }
      ]
    },
    {
      "move": "Down Special (Air)",
      "type": 4,
      "isUpSpecial": false,
      "startup": 39,
      "hitboxes": [
        {
          "hitbox": "Airborne Dthrow",
          "shieldSafety": {
            "isProjectile": true,
            "isStun": true,
            "min": 4,
            "max": 4
          },
          "shieldRaw": "4",
          "damage": 6,
          "knockbackGrowth": 30,
          "baseKnockback": 60,
          "setKnockback": 0,
          "angle": 70,
          "endlag": null
        },
        {
          "hitbox": "Airborne Uthrow",
          "shieldSafety": {
            "isProjectile": true,
            "isStun": true,
            "min": 4,
            "max": 4
          },
          "shieldRaw": "4",
          "damage": 5,
          "knockbackGrowth": 30,
          "baseKnockback": 60,
          "setKnockback": 0,
          "angle": 70,
          "endlag": null
        },
        {
          "hitbox": "Airborne Fthrow",
          "shieldSafety": {
            "isProjectile": true,
            "isStun": true,
            "min": 4,
            "max": 4
          },
          "shieldRaw": "4",
          "damage": 5,
          "knockbackGrowth": 30,
          "baseKnockback": 60,
          "setKnockback": 0,
          "angle": 70,
          "endlag": null
        }
      ]
    }
  ]
}
